lockable/__init__.py
lockable/client.py
lockable/config.py
lockable/exceptions.py
lockable/lock.py
lockable.dev-0.1.2.dist-info/LICENSE
lockable.dev-0.1.2.dist-info/METADATA
lockable.dev-0.1.2.dist-info/WHEEL
lockable.dev-0.1.2.dist-info/top_level.txt
lockable.dev-0.1.2.dist-info/RECORD
