Metadata-Version: 2.1
Name: lockable.dev
Version: 0.1.2
Summary: Official Python client for https://lockable.dev
Home-page: https://github.com/lockable-dev/lockable-py
Author: lockable-dev
Author-email: dev@lockable.dev
Project-URL: Lockable Website, https://lockable.dev
Project-URL: Documentation, https://docs.lockable.dev
Project-URL: Source Code, https://github.com/lockable-dev/lockable-py
Classifier: Programming Language :: Python :: 3
Classifier: License :: OSI Approved :: MIT License
Classifier: Operating System :: OS Independent
Requires-Python: >=3.6
License-File: LICENSE
